pretix_hide_add_to_calendar/__init__.py
pretix_hide_add_to_calendar/signals.py
pretix_hide_add_to_calendar/locale/de/LC_MESSAGES/django.mo
pretix_hide_add_to_calendar/locale/de/LC_MESSAGES/django.po
pretix_hide_add_to_calendar/locale/de_Informal/.gitkeep
pretix_hide_add_to_calendar/locale/de_Informal/LC_MESSAGES/django.mo
pretix_hide_add_to_calendar/locale/de_Informal/LC_MESSAGES/django.po
pretix_hide_add_to_calendar/static/pretix_hide_add_to_calendar/.gitkeep
pretix_hide_add_to_calendar/static/pretix_hide_add_to_calendar/style.css
pretix_hide_add_to_calendar/templates/pretix_hide_add_to_calendar/.gitkeep
pretix_hide_add_to_calendar/templates/pretix_hide_add_to_calendar/presale_head.html
pretix_hide_add_to_calendar-1.0.0.dist-info/LICENSE
pretix_hide_add_to_calendar-1.0.0.dist-info/METADATA
pretix_hide_add_to_calendar-1.0.0.dist-info/WHEEL
pretix_hide_add_to_calendar-1.0.0.dist-info/entry_points.txt
pretix_hide_add_to_calendar-1.0.0.dist-info/top_level.txt
pretix_hide_add_to_calendar-1.0.0.dist-info/RECORD
