Metadata-Version: 2.1
Name: pretix-hide-add-to-calendar
Version: 1.0.0
Summary: Hide Add to calendar link
Home-page: https://github.com/pretix-unofficial/pretix-hide-add-to-calendar
Author: RM
Author-email: support@pretix.eu
License: Apache
Platform: UNKNOWN
